{
    "detections": [
        {
            "bbox": {
                "height": 70.93375396728516,
                "width": 68.8033218383789,
                "x": 1109.7509765625,
                "y": 301.0391540527344
            },
            "class_id": 0,
            "class_name": "tennis",
            "confidence": 0.579519510269165
        },
        {
            "bbox": {
                "height": 85.33539581298828,
                "width": 86.90464782714844,
                "x": 385.4077453613281,
                "y": 369.3591613769531
            },
            "class_id": 0,
            "class_name": "tennis",
            "confidence": 0.5688585638999939
        },
        {
            "bbox": {
                "height": 87.06100463867188,
                "width": 86.04631042480469,
                "x": 954.9505004882813,
                "y": 343.3872985839844
            },
            "class_id": 0,
            "class_name": "tennis",
            "confidence": 0.5464057922363281
        },
        {
            "bbox": {
                "height": 71.04974365234375,
                "width": 70.89303588867188,
                "x": 686.7200317382813,
                "y": 324.0216369628906
            },
            "class_id": 0,
            "class_name": "tennis",
            "confidence": 0.5310612916946411
        },
        {
            "bbox": {
                "height": 81.10686492919922,
                "width": 71.34783935546875,
                "x": 617.6592407226563,
                "y": 345.0339050292969
            },
            "class_id": 0,
            "class_name": "tennis",
            "confidence": 0.45896270871162415
        },
        {
            "bbox": {
                "height": 83.97541809082031,
                "width": 86.09667205810547,
                "x": 656.9061889648438,
                "y": 369.78131103515625
            },
            "class_id": 0,
            "class_name": "tennis",
            "confidence": 0.435458242893219
        }
    ],
    "metrics": {
        "mAP50": 0.9090909957885742,
        "mAP50-95": 0.636363685131073,
        "precision": 1.0,
        "recall": 1.0
    },
    "model_name": "tennis_detect_640x640_bayese_nv12",
    "performance": {
        "fps": 76.92308044433594,
        "inference_time": 8.0,
        "postprocess_time": 0.0,
        "preprocess_time": 5.0,
        "total_time": 13.0
    },
    "task_id": "1_186",
    "task_type": "detection"
}
